{
  "L": "zh",
  "attack": "uni_l",
  "threshold": 0.95,
  "threshold_free": 0.9,
  "ran_full": true,
  "clean_acc": {
    "en": 0.859,
    "zh": 0.914
  },
  "baseline_acc": {
    "en": 0.72,
    "zh": 0.403
  },
  "baseline_asr": {
    "en": 0.017,
    "zh": 0.584
  },
  "defense": {
    "en": {
      "acc": 0.721,
      "asr": 0.026,
      "baseline_acc": 0.72,
      "baseline_asr": 0.017
    },
    "zh": {
      "acc": 0.624,
      "asr": 0.273,
      "baseline_acc": 0.403,
      "baseline_asr": 0.584
    },
    "mean_acc": 0.6725
  },
  "clean_deg": {
    "en": {
      "baseline_acc": 0.859,
      "masked_acc": 0.837,
      "delta_acc": -0.02200000000000002
    },
    "zh": {
      "baseline_acc": 0.914,
      "masked_acc": 0.907,
      "delta_acc": -0.007000000000000006
    }
  },
  "coverage": 0.06558663504464286,
  "mean_acc": 0.6725,
  "mean_clean_delta": -0.014500000000000013,
  "cost": 4
}